featuretools_ta1/__init__.py
featuretools_ta1/config.py
featuretools_ta1/multi_table.py
featuretools_ta1/normalization.py
featuretools_ta1/semantic_types.py
featuretools_ta1/single_table.py
featuretools_ta1/utils.py
featuretools_ta1/pipelines/__init__.py
featuretools_ta1/pipelines/dfs.py
pipeline_tests/__init__.py
pipeline_tests/pipeline_with_no_featuretools_primitives.py
pipeline_tests/test_1491_one_hundred_plants_margin.py
pipeline_tests/test_196_autoMpg.py
pipeline_tests/test_196_autoMpg_max_features.py
pipeline_tests/test_32_wikiqa.py
pipeline_tests/test_32_wikiqa_max_features.py
pipeline_tests/test_LL0_1100_popularkids.py
pipeline_tests/test_LL0_acled_reduced.py
pipeline_tests/test_LL1_50words.py
pipeline_tests/test_LL1_736_population_spawn.py
pipeline_tests/test_LL1_736_population_spawn_simpler.py
pipeline_tests/test_LL1_736_stock_market.py
pipeline_tests/test_LL1_retail_sales_binary.py
pipeline_tests/test_LL1_retail_sales_multi.py
pipeline_tests/test_LL1_retail_sales_total_multitable.py
pipeline_tests/test_LL1_retail_sales_total_singletable.py
pipeline_tests/test_kaggle_music_hackathon_multitable.py
pipeline_tests/test_kaggle_music_hackathon_singletable.py
pipeline_tests/test_loan_status_multitable.py
pipeline_tests/test_loan_status_singletable.py
pipeline_tests/test_uu2_gp_hyperparameter_estimation.py
pipeline_tests/utils.py
featuretools_ta1-0.7.4.dist-info/LICENSE.txt
featuretools_ta1-0.7.4.dist-info/METADATA
featuretools_ta1-0.7.4.dist-info/WHEEL
featuretools_ta1-0.7.4.dist-info/entry_points.txt
featuretools_ta1-0.7.4.dist-info/top_level.txt
featuretools_ta1-0.7.4.dist-info/RECORD
